README.md
setup.py
asyncs/__init__.py
asyncs/logger.py
asyncs/middleware.py
asyncs/request.py
asyncs/router.py
asyncs/server.py
asyncs.egg-info/PKG-INFO
asyncs.egg-info/SOURCES.txt
asyncs.egg-info/dependency_links.txt
asyncs.egg-info/requires.txt
asyncs.egg-info/top_level.txt
asyncs/response/__init__.py
asyncs/response/base.py
asyncs/response/html.py
asyncs/response/json.py
asyncs/response/text.py