Metadata-Version: 2.1
Name: asyncs
Version: 1.0.0
Summary: A simple asynchronous web library based on aiohttp.
Home-page: https://github.com/sscefalix/asyncs
Author: sscefalix
Author-email: sscefalix@gmail.com
Project-URL: Bug Reports, https://github.com/sscefalix/asyncs/issues
Project-URL: Source, https://github.com/sscefalix/asyncs/
Keywords: web,aiohttp,asyncs,fastapi,web server
Requires-Python: >=3.10, <4
Requires-Dist: jinja2
Requires-Dist: aiohttp
